{
	"info": {
		"_postman_id": "ab003288-497d-4bb2-bc28-024c1e310e54",
		"name": "AutoCompany",
		"schema": "https://schema.getpostman.com/json/collection/v2.1.0/collection.json",
		"_exporter_id": "14213224"
	},
	"item": [
		{
			"name": "Products",
			"protocolProfileBehavior": {
				"disableBodyPruning": true
			},
			"request": {
				"method": "GET",
				"header": [
					{
						"key": "Authorization",
						"value": "Token 98c5686f15e32bb532d039e7a90d697a1537118d",
						"type": "text",
						"disabled": true
					}
				],
				"body": {
					"mode": "raw",
					"raw": "",
					"options": {
						"raw": {
							"language": "json"
						}
					}
				},
				"url": {
					"raw": "http://127.0.0.1:8000/api/products/?page=1&page_size=5",
					"protocol": "http",
					"host": [
						"127",
						"0",
						"0",
						"1"
					],
					"port": "8000",
					"path": [
						"api",
						"products",
						""
					],
					"query": [
						{
							"key": "page",
							"value": "1"
						},
						{
							"key": "page_size",
							"value": "5"
						}
					]
				}
			},
			"response": []
		},
		{
			"name": "User register",
			"request": {
				"method": "POST",
				"header": [
					{
						"key": "Content-Type",
						"value": "application/json",
						"type": "text",
						"disabled": true
					}
				],
				"body": {
					"mode": "raw",
					"raw": "{\n    \"email\": \"pasand@gmail.com\",\n    \"username\": \"pasand\",\n    \"password\": \"123\"\n}",
					"options": {
						"raw": {
							"language": "json"
						}
					}
				},
				"url": {
					"raw": "http://localhost:8000/api/register/",
					"protocol": "http",
					"host": [
						"localhost"
					],
					"port": "8000",
					"path": [
						"api",
						"register",
						""
					]
				}
			},
			"response": []
		},
		{
			"name": "Registered user token",
			"request": {
				"method": "POST",
				"header": [],
				"body": {
					"mode": "raw",
					"raw": "{\n    \"username\": \"pasand\",\n    \"password\": \"123\"\n}",
					"options": {
						"raw": {
							"language": "json"
						}
					}
				},
				"url": {
					"raw": "http://localhost:8000/api/api-token-auth/",
					"protocol": "http",
					"host": [
						"localhost"
					],
					"port": "8000",
					"path": [
						"api",
						"api-token-auth",
						""
					]
				}
			},
			"response": []
		},
		{
			"name": "Product detail",
			"request": {
				"method": "GET",
				"header": [],
				"url": {
					"raw": "http://127.0.0.1:8000/api/products/3",
					"protocol": "http",
					"host": [
						"127",
						"0",
						"0",
						"1"
					],
					"port": "8000",
					"path": [
						"api",
						"products",
						"3"
					]
				}
			},
			"response": []
		},
		{
			"name": "Add Product Admin",
			"request": {
				"method": "POST",
				"header": [
					{
						"key": "Authorization",
						"value": "Token 98c5686f15e32bb532d039e7a90d697a1537118d",
						"type": "text"
					}
				],
				"body": {
					"mode": "raw",
					"raw": "{\n    \"name\": \"Head Light\",\n    \"description\": \"Head light for Tesla\",\n    \"price\": \"1000.00\"\n}",
					"options": {
						"raw": {
							"language": "json"
						}
					}
				},
				"url": {
					"raw": "http://127.0.0.1:8000/api/admin/products/",
					"protocol": "http",
					"host": [
						"127",
						"0",
						"0",
						"1"
					],
					"port": "8000",
					"path": [
						"api",
						"admin",
						"products",
						""
					]
				}
			},
			"response": []
		},
		{
			"name": "Update Product Admin",
			"request": {
				"method": "PUT",
				"header": [
					{
						"key": "Authorization",
						"value": "Token 98c5686f15e32bb532d039e7a90d697a1537118d",
						"type": "text"
					}
				],
				"body": {
					"mode": "raw",
					"raw": "{\n    \"name\": \"LED Head Light\",\n    \"description\": \"LED Head light for Tesla\",\n    \"price\": \"1000.00\"\n}",
					"options": {
						"raw": {
							"language": "json"
						}
					}
				},
				"url": {
					"raw": "http://127.0.0.1:8000/api/products/3/",
					"protocol": "http",
					"host": [
						"127",
						"0",
						"0",
						"1"
					],
					"port": "8000",
					"path": [
						"api",
						"products",
						"3",
						""
					]
				}
			},
			"response": []
		},
		{
			"name": "Delete Product Admin",
			"request": {
				"method": "DELETE",
				"header": [
					{
						"key": "Authorization",
						"value": "Token 98c5686f15e32bb532d039e7a90d697a1537118d",
						"type": "text"
					}
				],
				"url": {
					"raw": "http://127.0.0.1:8000/api/products/3/",
					"protocol": "http",
					"host": [
						"127",
						"0",
						"0",
						"1"
					],
					"port": "8000",
					"path": [
						"api",
						"products",
						"3",
						""
					]
				}
			},
			"response": []
		},
		{
			"name": "Add to cart",
			"request": {
				"method": "POST",
				"header": [
					{
						"key": "Authorization",
						"value": "Token 431a43491b1896fa11cc735ff0441d9b3f494288",
						"type": "text"
					}
				],
				"body": {
					"mode": "raw",
					"raw": "{\n    \"product_id\": 9,\n    \"quantity\": 7\n}\n",
					"options": {
						"raw": {
							"language": "json"
						}
					}
				},
				"url": {
					"raw": "http://127.0.0.1:8000/api/cart/add/",
					"protocol": "http",
					"host": [
						"127",
						"0",
						"0",
						"1"
					],
					"port": "8000",
					"path": [
						"api",
						"cart",
						"add",
						""
					]
				}
			},
			"response": []
		},
		{
			"name": "View Cart",
			"request": {
				"method": "GET",
				"header": [
					{
						"key": "Authorization",
						"value": "Token 431a43491b1896fa11cc735ff0441d9b3f494288",
						"type": "text"
					}
				],
				"url": {
					"raw": "http://127.0.0.1:8000/api/cart/view/",
					"protocol": "http",
					"host": [
						"127",
						"0",
						"0",
						"1"
					],
					"port": "8000",
					"path": [
						"api",
						"cart",
						"view",
						""
					]
				}
			},
			"response": []
		},
		{
			"name": "Remove cart item",
			"request": {
				"method": "DELETE",
				"header": [
					{
						"key": "Authorization",
						"value": "Token 431a43491b1896fa11cc735ff0441d9b3f494288",
						"type": "text"
					}
				],
				"url": {
					"raw": "http://127.0.0.1:8000/api/cart/remove/5/",
					"protocol": "http",
					"host": [
						"127",
						"0",
						"0",
						"1"
					],
					"port": "8000",
					"path": [
						"api",
						"cart",
						"remove",
						"5",
						""
					]
				}
			},
			"response": []
		},
		{
			"name": "Order",
			"request": {
				"method": "POST",
				"header": [
					{
						"key": "Authorization",
						"value": "Token 431a43491b1896fa11cc735ff0441d9b3f494288",
						"type": "text"
					}
				],
				"body": {
					"mode": "raw",
					"raw": "{\n    \"delivery_date\": \"2024-02-01\"\n}",
					"options": {
						"raw": {
							"language": "json"
						}
					}
				},
				"url": {
					"raw": "http://127.0.0.1:8000/api/checkout/",
					"protocol": "http",
					"host": [
						"127",
						"0",
						"0",
						"1"
					],
					"port": "8000",
					"path": [
						"api",
						"checkout",
						""
					]
				}
			},
			"response": []
		}
	]
}